dicttoxunit.py
setup.py
dicttoxunit.egg-info/PKG-INFO
dicttoxunit.egg-info/SOURCES.txt
dicttoxunit.egg-info/dependency_links.txt
dicttoxunit.egg-info/requires.txt
dicttoxunit.egg-info/top_level.txt
test/test_dicttoxunit.py