Metadata-Version: 1.1
Name: dicttoxunit
Version: 0.0.3
Summary: Convert dictionary to xunit xml format
Home-page: https://github.com/dijam/dicttoxunit
Author: Majid Garmaroudi
Author-email: majid.sadeghi@gmail.com
License: MIT
Platform: all
Classifier: Intended Audience :: Developers
Classifier: License :: OSI Approved :: MIT License
Classifier: Operating System :: OS Independent
Classifier: Programming Language :: Python
Classifier: Programming Language :: Python :: 2
Classifier: Programming Language :: Python :: 2.5
Classifier: Programming Language :: Python :: 2.6
Classifier: Programming Language :: Python :: 2.7
Classifier: Programming Language :: Python :: 3
Classifier: Programming Language :: Python :: 3.2
Classifier: Programming Language :: Python :: 3.3
Classifier: Topic :: Text Processing :: Markup :: XML
